commitizen_xcodeproj/__init__.py
commitizen_xcodeproj/xcodeproj_version_provider.py
commitizen_xcodeproj-0.2.1.dist-info/LICENSE
commitizen_xcodeproj-0.2.1.dist-info/METADATA
commitizen_xcodeproj-0.2.1.dist-info/WHEEL
commitizen_xcodeproj-0.2.1.dist-info/entry_points.txt
commitizen_xcodeproj-0.2.1.dist-info/RECORD
