Metadata-Version: 2.1
Name: commitizen-xcodeproj
Version: 0.2.1
Summary: Commitizen version provider for Xcode projects.
Author: Karsten Silkenbäumer
Author-email: 993392+kassi@users.noreply.github.com
Requires-Python: >=3.10,<4.0
Classifier: Programming Language :: Python :: 3
Classifier: Programming Language :: Python :: 3.10
Classifier: Programming Language :: Python :: 3.11
Classifier: Programming Language :: Python :: 3.12
Requires-Dist: deepmerge (>=1.1.1,<2.0.0)
